LICENSE
README.md
exasol/slc_ci/cli/cli.py
exasol/slc_ci/cli/commands/__init__.py
exasol/slc_ci/cli/commands/check_if_build_needed.py
exasol/slc_ci/cli/commands/export_and_scan_vulnerabilities.py
exasol/slc_ci/cli/commands/get_build_runner.py
exasol/slc_ci/cli/commands/get_flavors.py
exasol/slc_ci/cli/commands/get_test_matrix.py
exasol/slc_ci/cli/commands/prepare_test_container.py
exasol/slc_ci/cli/commands/run_tests.py
exasol/slc_ci/cli/main.py
exasol/slc_ci/cli/options/__init__.py
exasol/slc_ci/cli/options/branch_options.py
exasol/slc_ci/cli/options/docker_options.py
exasol/slc_ci/cli/options/flavor_options.py
exasol/slc_ci/cli/options/github_options.py
exasol/slc_ci/cli/options/test_options.py
exasol/slc_ci/lib/branch_config.py
exasol/slc_ci/lib/check_if_build_needed.py
exasol/slc_ci/lib/ci_build.py
exasol/slc_ci/lib/ci_export.py
exasol/slc_ci/lib/ci_prepare.py
exasol/slc_ci/lib/ci_push.py
exasol/slc_ci/lib/ci_push_test_container.py
exasol/slc_ci/lib/ci_security_scan.py
exasol/slc_ci/lib/ci_step_output_printer.py
exasol/slc_ci/lib/ci_test.py
exasol/slc_ci/lib/export_and_scan_vulnerabilities.py
exasol/slc_ci/lib/get_build_config_model.py
exasol/slc_ci/lib/get_build_runner.py
exasol/slc_ci/lib/get_flavor_ci_model.py
exasol/slc_ci/lib/get_flavors.py
exasol/slc_ci/lib/get_test_matrix.py
exasol/slc_ci/lib/git_access.py
exasol/slc_ci/lib/github_access.py
exasol/slc_ci/lib/prepare_test_container.py
exasol/slc_ci/lib/run_tests.py
exasol/slc_ci/model/build_config_model.py
exasol/slc_ci/model/build_mode.py
exasol/slc_ci/model/flavor_ci_model.py
exasol/slc_ci/model/github_event.py
exasol/slc_ci/version.py
exasol_script_languages_container_ci-4.0.1.dist-info/LICENSE
exasol_script_languages_container_ci-4.0.1.dist-info/METADATA
exasol_script_languages_container_ci-4.0.1.dist-info/WHEEL
exasol_script_languages_container_ci-4.0.1.dist-info/entry_points.txt
exasol_script_languages_container_ci-4.0.1.dist-info/RECORD
