Metadata-Version: 2.3
Name: exasol-script-languages-container-ci
Version: 4.0.1
Summary: Implements CI builds for script-language-container.
License: MIT
Author: Thomas Uebensee
Author-email: Thomas Uebensee <ext.thomas.uebensee@exasol.com>
Requires-Python: >=3.10, <4.0
Classifier: License :: OSI Approved :: MIT License
Classifier: Programming Language :: Python :: 3
Classifier: Programming Language :: Python :: 3.10
Classifier: Programming Language :: Python :: 3.11
Classifier: Programming Language :: Python :: 3.12
Classifier: Programming Language :: Python :: 3.13
Requires-Dist: GitPython (>=3.1.0,<4.0.0)
Requires-Dist: PyGithub (>=2.3.0,<3.0.0)
Requires-Dist: click (>=8.1.7,<9.0.0)
Requires-Dist: exasol-script-languages-container-tool (>=3.2.0,<4.0.0)
Requires-Dist: setuptools (>=80.0.0)
